{
  "city": "Karachi",
  "target_date": "2026-04-15",
  "captured_at_utc": "2026-04-16T15:00:01.562181+00:00",
  "station_id": "OPKC:9:PK",
  "source": "wu_icao_history",
  "daily_high_f": 93,
  "observation_count": 48,
  "data_version": "oracle_shadow_v1",
  "wu_raw_payload": {
    "metadata": {
      "language": "en-US",
      "transaction_id": "1776351623625:753989931",
      "version": "1",
      "location_id": "OPKC:9:PK",
      "units": "e",
      "expire_time_gmt": 1776355223,
      "status_code": 200
    },
    "observations": [
      {
        "key": "OPKC",
        "class": "observation",
        "expire_time_gmt": 1776200400,
        "obs_id": "OPKC",
        "obs_name": "Karachi",
        "valid_time_gmt": 1776193200,
        "day_ind": "N",
        "temp": 81,
        "wx_icon": 21,
        "icon_extd": 2100,
        "wx_phrase": "Haze",
        "pressure_tend": null,
        "pressure_desc": null,
        "dewPt": 64,
        "heat_index": 82,
        "rh": 58,
        "pressure": 29.69,
        "vis": 3,
        "wc": 81,
        "wdir": 270,
        "wdir_cardinal": "W",
        "gust": null,
        "wspd": 7,
        "max_temp": null,
        "min_temp": null,
        "precip_total": null,
        "precip_hrly": null,
        "snow_hrly": null,
        "uv_desc": "Low",
        "feels_like": 82,
        "uv_index": 0,
        "qualifier": null,
        "qualifier_svrty": null,
        "blunt_phrase": null,
        "terse_phrase": null,
        "clds": "CLR",
        "water_temp": null,
        "primary_wave_period": null,
        "primary_wave_height": null,
        "primary_swell_period": null,
        "primary_swell_height": null,
        "primary_swell_direction": null,
        "secondary_swell_period": null,
        "secondary_swell_height": null,
        "secondary_swell_direction": null
      },
      {
        "key": "OPKC",
        "class": "observation",
        "expire_time_gmt": 1776202200,
        "obs_id": "OPKC",
        "obs_name": "Karachi",
        "valid_time_gmt": 1776195000,
        "day_ind": "N",
        "temp": 81,
        "wx_icon": 21,
        "icon_extd": 2100,
        "wx_phrase": "Haze",
        "pressure_tend": null,
        "pressure_desc": null,
        "dewPt": 64,
        "heat_index": 82,
        "rh": 58,
        "pressure": 29.69,
        "vis": 3,
        "wc": 81,
        "wdir": 270,
        "wdir_cardinal": "W",
        "gust": null,
        "wspd": 8,
        "max_temp": null,
        "min_temp": null,
        "precip_total": null,
        "precip_hrly": null,
        "snow_hrly": null,
        "uv_desc": "Low",
        "feels_like": 82,
        "uv_index": 0,
        "qualifier": null,
        "qualifier_svrty": null,
        "blunt_phrase": null,
        "terse_phrase": null,
        "clds": "CLR",
        "water_temp": null,
        "primary_wave_period": null,
        "primary_wave_height": null,
        "primary_swell_period": null,
        "primary_swell_height": null,
        "primary_swell_direction": null,
        "secondary_swell_period": null,
        "secondary_swell_height": null,
        "secondary_swell_direction": null
      },
      {
        "key": "OPKC",
        "class": "observation",
        "expire_time_gmt": 1776204000,
        "obs_id": "OPKC",
        "obs_name": "Karachi",
        "valid_time_gmt": 1776196800,
        "day_ind": "N",
        "temp": 79,
        "wx_icon": 21,
        "icon_extd": 2100,
        "wx_phrase": "Haze",
        "pressure_tend": null,
        "pressure_desc": null,
        "dewPt": 64,
        "heat_index": 81,
        "rh": 61,
        "pressure": 29.66,
        "vis": 3,
        "wc": 79,
        "wdir": 270,
        "wdir_cardinal": "W",
        "gust": null,
        "wspd": 3,
        "max_temp": null,
        "min_temp": null,
        "precip_total": null,
        "precip_hrly": null,
        "snow_hrly": null,
        "uv_desc": "Low",
        "feels_like": 81,
        "uv_index": 0,
        "qualifier": null,
        "qualifier_svrty": null,
        "blunt_phrase": null,
        "terse_phrase": null,
        "clds": "CLR",
        "water_temp": null,
        "primary_wave_period": null,
        "primary_wave_height": null,
        "primary_swell_period": null,
        "primary_swell_height": null,
        "primary_swell_direction": null,
        "secondary_swell_period": null,
        "secondary_swell_height": null,
        "secondary_swell_direction": null
      },
      {
        "key": "OPKC",
        "class": "observation",
        "expire_time_gmt": 1776205800,
        "obs_id": "OPKC",
        "obs_name": "Karachi",
        "valid_time_gmt": 1776198600,
        "day_ind": "N",
        "temp": 79,
        "wx_icon": 21,
        "icon_extd": 2100,
        "wx_phrase": "Haze",
        "pressure_tend": null,
        "pressure_desc": null,
        "dewPt": 64,
        "heat_index": 81,
        "rh": 61,
        "pressure": 29.66,
        "vis": 3,
        "wc": 79,
        "wdir": 240,
        "wdir_cardinal": "WSW",
        "gust": null,
        "wspd": 5,
        "max_temp": null,
        "min_temp": null,
        "precip_total": null,
        "precip_hrly": null,
        "snow_hrly": null,
        "uv_desc": "Low",
        "feels_like": 81,
        "uv_index": 0,
        "qualifier": null,
        "qualifier_svrty": null,
        "blunt_phrase": null,
        "terse_phrase": null,
        "clds": "CLR",
        "water_temp": null,
        "primary_wave_period": null,
        "primary_wave_height": null,
        "primary_swell_period": null,
        "primary_swell_height": null,
        "primary_swell_direction": null,
        "secondary_swell_period": null,
        "secondary_swell_height": null,
        "secondary_swell_direction": null
      },
      {
        "key": "OPKC",
        "class": "observation",
        "expire_time_gmt": 1776207600,
        "obs_id": "OPKC",
        "obs_name": "Karachi",
        "valid_time_gmt": 1776200400,
        "day_ind": "N",
        "temp": 77,
        "wx_icon": 21,
        "icon_extd": 2100,
        "wx_phrase": "Haze",
        "pressure_tend": null,
        "pressure_desc": null,
        "dewPt": 66,
        "heat_index": 79,
        "rh": 69,
        "pressure": 29.66,
        "vis": 3,
        "wc": 77,
        "wdir": 240,
        "wdir_cardinal": "WSW",
        "gust": null,
        "wspd": 6,
        "max_temp": null,
        "min_temp": null,
        "precip_total": null,
        "precip_hrly": null,
        "snow_hrly": null,
        "uv_desc": "Low",
        "feels_like": 79,
        "uv_index": 0,
        "qualifier": null,
        "qualifier_svrty": null,
        "blunt_phrase": null,
        "terse_phrase": null,
        "clds": "CLR",
        "water_temp": null,
        "primary_wave_period": null,
        "primary_wave_height": null,
        "primary_swell_period": null,
        "primary_swell_height": null,
        "primary_swell_direction": null,
        "secondary_swell_period": null,
        "secondary_swell_height": null,
        "secondary_swell_direction": null
      },
      {
        "key": "OPKC",
        "class": "observation",
        "expire_time_gmt": 1776209400,
        "obs_id": "OPKC",
        "obs_name": "Karachi",
        "valid_time_gmt": 1776202200,
        "day_ind": "N",
        "temp": 77,
        "wx_icon": 21,
        "icon_extd": 2100,
        "wx_phrase": "Haze",
        "pressure_tend": null,
        "pressure_desc": null,
        "dewPt": 66,
        "heat_index": 79,
        "rh": 69,
        "pressure": 29.63,
        "vis": 3,
        "wc": 77,
        "wdir": 260,
        "wdir_cardinal": "W",
        "gust": null,
        "wspd": 7,
        "max_temp": null,
        "min_temp": null,
        "precip_total": null,
        "precip_hrly": null,
        "snow_hrly": null,
        "uv_desc": "Low",
        "feels_like": 79,
        "uv_index": 0,
        "qualifier": null,
        "qualifier_svrty": null,
        "blunt_phrase": null,
        "terse_phrase": null,
        "clds": "CLR",
        "water_temp": null,
        "primary_wave_period": null,
        "primary_wave_height": null,
        "primary_swell_period": null,
        "primary_swell_height": null,
        "primary_swell_direction": null,
        "secondary_swell_period": null,
        "secondary_swell_height": null,
        "secondary_swell_direction": null
      },
      {
        "key": "OPKC",
        "class": "observation",
        "expire_time_gmt": 1776211200,
        "obs_id": "OPKC",
        "obs_name": "Karachi",
        "valid_time_gmt": 1776204000,
        "day_ind": "N",
        "temp": 77,
        "wx_icon": 21,
        "icon_extd": 2100,
        "wx_phrase": "Haze",
        "pressure_tend": null,
        "pressure_desc": null,
        "dewPt": 66,
        "heat_index": 79,
        "rh": 69,
        "pressure": 29.63,
        "vis": 3,
        "wc": 77,
        "wdir": 270,
        "wdir_cardinal": "W",
        "gust": null,
        "wspd": 7,
        "max_temp": null,
        "min_temp": null,
        "precip_total": null,
        "precip_hrly": null,
        "snow_hrly": null,
        "uv_desc": "Low",
        "feels_like": 79,
        "uv_index": 0,
        "qualifier": null,
        "qualifier_svrty": null,
        "blunt_phrase": null,
        "terse_phrase": null,
        "clds": "CLR",
        "water_temp": null,
        "primary_wave_period": null,
        "primary_wave_height": null,
        "primary_swell_period": null,
        "primary_swell_height": null,
        "primary_swell_direction": null,
        "secondary_swell_period": null,
        "secondary_swell_height": null,
        "secondary_swell_direction": null
      },
      {
        "key": "OPKC",
        "class": "observation",
        "expire_time_gmt": 1776213000,
        "obs_id": "OPKC",
        "obs_name": "Karachi",
        "valid_time_gmt": 1776205800,
        "day_ind": "N",
        "temp": 79,
        "wx_icon": 21,
        "icon_extd": 2100,
        "wx_phrase": "Haze",
        "pressure_tend": null,
        "pressure_desc": null,
        "dewPt": 64,
        "heat_index": 81,
        "rh": 61,
        "pressure": 29.63,
        "vis": 3,
        "wc": 79,
        "wdir": 260,
        "wdir_cardinal": "W",
        "gust": null,
        "wspd": 8,
        "max_temp": null,
        "min_temp": null,
        "precip_total": null,
        "precip_hrly": null,
        "snow_hrly": null,
        "uv_desc": "Low",
        "feels_like": 81,
        "uv_index": 0,
        "qualifier": null,
        "qualifier_svrty": null,
        "blunt_phrase": null,
        "terse_phrase": null,
        "clds": "CLR",
        "water_temp": null,
        "primary_wave_period": null,
        "primary_wave_height": null,
        "primary_swell_period": null,
        "primary_swell_height": null,
        "primary_swell_direction": null,
        "secondary_swell_period": null,
        "secondary_swell_height": null,
        "secondary_swell_direction": null
      },
      {
        "key": "OPKC",
        "class": "observation",
        "expire_time_gmt": 1776214800,
        "obs_id": "OPKC",
        "obs_name": "Karachi",
        "valid_time_gmt": 1776207600,
        "day_ind": "N",
        "temp": 79,
        "wx_icon": 21,
        "icon_extd": 2100,
        "wx_phrase": "Haze",
        "pressure_tend": null,
        "pressure_desc": null,
        "dewPt": 64,
        "heat_index": 81,
        "rh": 61,
        "pressure": 29.6,
        "vis": 3,
        "wc": 79,
        "wdir": 290,
        "wdir_cardinal": "WNW",
        "gust": null,
        "wspd": 3,
        "max_temp": null,
        "min_temp": null,
        "precip_total": null,
        "precip_hrly": null,
        "snow_hrly": null,
        "uv_desc": "Low",
        "feels_like": 81,
        "uv_index": 0,
        "qualifier": null,
        "qualifier_svrty": null,
        "blunt_phrase": null,
        "terse_phrase": null,
        "clds": "CLR",
        "water_temp": null,
        "primary_wave_period": null,
        "primary_wave_height": null,
        "primary_swell_period": null,
        "primary_swell_height": null,
        "primary_swell_direction": null,
        "secondary_swell_period": null,
        "secondary_swell_height": null,
        "secondary_swell_direction": null
      },
      {
        "key": "OPKC",
        "class": "observation",
        "expire_time_gmt": 1776216600,
        "obs_id": "OPKC",
        "obs_name": "Karachi",
        "valid_time_gmt": 1776209400,
        "day_ind": "N",
        "temp": 79,
        "wx_icon": 21,
        "icon_extd": 2100,
        "wx_phrase": "Haze",
        "pressure_tend": null,
        "pressure_desc": null,
        "dewPt": 64,
        "heat_index": 81,
        "rh": 61,
        "pressure": 29.6,
        "vis": 3,
        "wc": 79,
        "wdir": 300,
        "wdir_cardinal": "WNW",
        "gust": null,
        "wspd": 5,
        "max_temp": null,
        "min_temp": null,
        "precip_total": null,
        "precip_hrly": null,
        "snow_hrly": null,
        "uv_desc": "Low",
        "feels_like": 81,
        "uv_index": 0,
        "qualifier": null,
        "qualifier_svrty": null,
        "blunt_phrase": null,
        "terse_phrase": null,
        "clds": "CLR",
        "water_temp": null,
        "primary_wave_period": null,
        "primary_wave_height": null,
        "primary_swell_period": null,
        "primary_swell_height": null,
        "primary_swell_direction": null,
        "secondary_swell_period": null,
        "secondary_swell_height": null,
        "secondary_swell_direction": null
      },
      {
        "key": "OPKC",
        "class": "observation",
        "expire_time_gmt": 1776218400,
        "obs_id": "OPKC",
        "obs_name": "Karachi",
        "valid_time_gmt": 1776211200,
        "day_ind": "N",
        "temp": 77,
        "wx_icon": 21,
        "icon_extd": 2100,
        "wx_phrase": "Haze",
        "pressure_tend": null,
        "pressure_desc": null,
        "dewPt": 66,
        "heat_index": 79,
        "rh": 69,
        "pressure": 29.6,
        "vis": 3,
        "wc": 77,
        "wdir": 300,
        "wdir_cardinal": "WNW",
        "gust": null,
        "wspd": 6,
        "max_temp": null,
        "min_temp": null,
        "precip_total": null,
        "precip_hrly": null,
        "snow_hrly": null,
        "uv_desc": "Low",
        "feels_like": 79,
        "uv_index": 0,
        "qualifier": null,
        "qualifier_svrty": null,
        "blunt_phrase": null,
        "terse_phrase": null,
        "clds": "CLR",
        "water_temp": null,
        "primary_wave_period": null,
        "primary_wave_height": null,
        "primary_swell_period": null,
        "primary_swell_height": null,
        "primary_swell_direction": null,
        "secondary_swell_period": null,
        "secondary_swell_height": null,
        "secondary_swell_direction": null
      },
      {
        "key": "OPKC",
        "class": "observation",
        "expire_time_gmt": 1776220200,
        "obs_id": "OPKC",
        "obs_name": "Karachi",
        "valid_time_gmt": 1776213000,
        "day_ind": "N",
        "temp": 77,
        "wx_icon": 21,
        "icon_extd": 2100,
        "wx_phrase": "Haze",
        "pressure_tend": null,
        "pressure_desc": null,
        "dewPt": 66,
        "heat_index": 79,
        "rh": 69,
        "pressure": 29.6,
        "vis": 3,
        "wc": 77,
        "wdir": 330,
        "wdir_cardinal": "NNW",
        "gust": null,
        "wspd": 6,
        "max_temp": null,
        "min_temp": null,
        "precip_total": null,
        "precip_hrly": null,
        "snow_hrly": null,
        "uv_desc": "Low",
        "feels_like": 79,
        "uv_index": 0,
        "qualifier": null,
        "qualifier_svrty": null,
        "blunt_phrase": null,
        "terse_phrase": null,
        "clds": "CLR",
        "water_temp": null,
        "primary_wave_period": null,
        "primary_wave_height": null,
        "primary_swell_period": null,
        "primary_swell_height": null,
        "primary_swell_direction": null,
        "secondary_swell_period": null,
        "secondary_swell_height": null,
        "secondary_swell_direction": null
      },
      {
        "key": "OPKC",
        "class": "observation",
        "expire_time_gmt": 1776222000,
        "obs_id": "OPKC",
        "obs_name": "Karachi",
        "valid_time_gmt": 1776214800,
        "day_ind": "D",
        "temp": 77,
        "wx_icon": 21,
        "icon_extd": 2100,
        "wx_phrase": "Haze",
        "pressure_tend": null,
        "pressure_desc": null,
        "dewPt": 68,
        "heat_index": 79,
        "rh": 74,
        "pressure": 29.6,
        "vis": 3,
        "wc": 77,
        "wdir": 310,
        "wdir_cardinal": "NW",
        "gust": null,
        "wspd": 6,
        "max_temp": null,
        "min_temp": null,
        "precip_total": null,
        "precip_hrly": null,
        "snow_hrly": null,
        "uv_desc": "Low",
        "feels_like": 79,
        "uv_index": 0,
        "qualifier": null,
        "qualifier_svrty": null,
        "blunt_phrase": null,
        "terse_phrase": null,
        "clds": "CLR",
        "water_temp": null,
        "primary_wave_period": null,
        "primary_wave_height": null,
        "primary_swell_period": null,
        "primary_swell_height": null,
        "primary_swell_direction": null,
        "secondary_swell_period": null,
        "secondary_swell_height": null,
        "secondary_swell_direction": null
      },
      {
        "key": "OPKC",
        "class": "observation",
        "expire_time_gmt": 1776223800,
        "obs_id": "OPKC",
        "obs_name": "Karachi",
        "valid_time_gmt": 1776216600,
        "day_ind": "D",
        "temp": 77,
        "wx_icon": 21,
        "icon_extd": 2100,
        "wx_phrase": "Haze",
        "pressure_tend": null,
        "pressure_desc": null,
        "dewPt": 68,
        "heat_index": 79,
        "rh": 74,
        "pressure": 29.6,
        "vis": 3,
        "wc": 77,
        "wdir": 300,
        "wdir_cardinal": "WNW",
        "gust": null,
        "wspd": 3,
        "max_temp": null,
        "min_temp": null,
        "precip_total": null,
        "precip_hrly": null,
        "snow_hrly": null,
        "uv_desc": "Low",
        "feels_like": 79,
        "uv_index": 0,
        "qualifier": null,
        "qualifier_svrty": null,
        "blunt_phrase": null,
        "terse_phrase": null,
        "clds": "CLR",
        "water_temp": null,
        "primary_wave_period": null,
        "primary_wave_height": null,
        "primary_swell_period": null,
        "primary_swell_height": null,
        "primary_swell_direction": null,
        "secondary_swell_period": null,
        "secondary_swell_height": null,
        "secondary_swell_direction": null
      },
      {
        "key": "OPKC",
        "class": "observation",
        "expire_time_gmt": 1776225600,
        "obs_id": "OPKC",
        "obs_name": "Karachi",
        "valid_time_gmt": 1776218400,
        "day_ind": "D",
        "temp": 75,
        "wx_icon": 21,
        "icon_extd": 2100,
        "wx_phrase": "Haze",
        "pressure_tend": null,
        "pressure_desc": null,
        "dewPt": 70,
        "heat_index": 75,
        "rh": 83,
        "pressure": 29.63,
        "vis": 3,
        "wc": 75,
        "wdir": 290,
        "wdir_cardinal": "WNW",
        "gust": null,
        "wspd": 5,
        "max_temp": null,
        "min_temp": null,
        "precip_total": null,
        "precip_hrly": null,
        "snow_hrly": null,
        "uv_desc": "Low",
        "feels_like": 75,
        "uv_index": 0,
        "qualifier": null,
        "qualifier_svrty": null,
        "blunt_phrase": null,
        "terse_phrase": null,
        "clds": "CLR",
        "water_temp": null,
        "primary_wave_period": null,
        "primary_wave_height": null,
        "primary_swell_period": null,
        "primary_swell_height": null,
        "primary_swell_direction": null,
        "secondary_swell_period": null,
        "secondary_swell_height": null,
        "secondary_swell_direction": null
      },
      {
        "key": "OPKC",
        "class": "observation",
        "expire_time_gmt": 1776227400,
        "obs_id": "OPKC",
        "obs_name": "Karachi",
        "valid_time_gmt": 1776220200,
        "day_ind": "D",
        "temp": 75,
        "wx_icon": 21,
        "icon_extd": 2100,
        "wx_phrase": "Haze",
        "pressure_tend": null,
        "pressure_desc": null,
        "dewPt": 70,
        "heat_index": 75,
        "rh": 83,
        "pressure": 29.63,
        "vis": 2,
        "wc": 75,
        "wdir": null,
        "wdir_cardinal": "CALM",
        "gust": null,
        "wspd": 0,
        "max_temp": null,
        "min_temp": null,
        "precip_total": null,
        "precip_hrly": null,
        "snow_hrly": null,
        "uv_desc": "Low",
        "feels_like": 75,
        "uv_index": 1,
        "qualifier": null,
        "qualifier_svrty": null,
        "blunt_phrase": null,
        "terse_phrase": null,
        "clds": "CLR",
        "water_temp": null,
        "primary_wave_period": null,
        "primary_wave_height": null,
        "primary_swell_period": null,
        "primary_swell_height": null,
        "primary_swell_direction": null,
        "secondary_swell_period": null,
        "secondary_swell_height": null,
        "secondary_swell_direction": null
      },
      {
        "key": "OPKC",
        "class": "observation",
        "expire_time_gmt": 1776229200,
        "obs_id": "OPKC",
        "obs_name": "Karachi",
        "valid_time_gmt": 1776222000,
        "day_ind": "D",
        "temp": 81,
        "wx_icon": 21,
        "icon_extd": 2100,
        "wx_phrase": "Haze",
        "pressure_tend": null,
        "pressure_desc": null,
        "dewPt": 70,
        "heat_index": 84,
        "rh": 70,
        "pressure": 29.66,
        "vis": 2,
        "wc": 81,
        "wdir": null,
        "wdir_cardinal": "CALM",
        "gust": null,
        "wspd": 0,
        "max_temp": null,
        "min_temp": null,
        "precip_total": null,
        "precip_hrly": null,
        "snow_hrly": null,
        "uv_desc": "Low",
        "feels_like": 84,
        "uv_index": 1,
        "qualifier": null,
        "qualifier_svrty": null,
        "blunt_phrase": null,
        "terse_phrase": null,
        "clds": "CLR",
        "water_temp": null,
        "primary_wave_period": null,
        "primary_wave_height": null,
        "primary_swell_period": null,
        "primary_swell_height": null,
        "primary_swell_direction": null,
        "secondary_swell_period": null,
        "secondary_swell_height": null,
        "secondary_swell_direction": null
      },
      {
        "key": "OPKC",
        "class": "observation",
        "expire_time_gmt": 1776231000,
        "obs_id": "OPKC",
        "obs_name": "Karachi",
        "valid_time_gmt": 1776223800,
        "day_ind": "D",
        "temp": 82,
        "wx_icon": 21,
        "icon_extd": 2100,
        "wx_phrase": "Haze",
        "pressure_tend": null,
        "pressure_desc": null,
        "dewPt": 68,
        "heat_index": 85,
        "rh": 62,
        "pressure": 29.66,
        "vis": 1,
        "wc": 82,
        "wdir": 240,
        "wdir_cardinal": "WSW",
        "gust": null,
        "wspd": 5,
        "max_temp": null,
        "min_temp": null,
        "precip_total": null,
        "precip_hrly": null,
        "snow_hrly": null,
        "uv_desc": "Low",
        "feels_like": 85,
        "uv_index": 2,
        "qualifier": null,
        "qualifier_svrty": null,
        "blunt_phrase": null,
        "terse_phrase": null,
        "clds": "CLR",
        "water_temp": null,
        "primary_wave_period": null,
        "primary_wave_height": null,
        "primary_swell_period": null,
        "primary_swell_height": null,
        "primary_swell_direction": null,
        "secondary_swell_period": null,
        "secondary_swell_height": null,
        "secondary_swell_direction": null
      },
      {
        "key": "OPKC",
        "class": "observation",
        "expire_time_gmt": 1776232800,
        "obs_id": "OPKC",
        "obs_name": "Karachi",
        "valid_time_gmt": 1776225600,
        "day_ind": "D",
        "temp": 82,
        "wx_icon": 21,
        "icon_extd": 2100,
        "wx_phrase": "Haze",
        "pressure_tend": null,
        "pressure_desc": null,
        "dewPt": 70,
        "heat_index": 86,
        "rh": 66,
        "pressure": 29.66,
        "vis": 1,
        "wc": 82,
        "wdir": 220,
        "wdir_cardinal": "SW",
        "gust": null,
        "wspd": 6,
        "max_temp": null,
        "min_temp": null,
        "precip_total": null,
        "precip_hrly": null,
        "snow_hrly": null,
        "uv_desc": "Moderate",
        "feels_like": 86,
        "uv_index": 4,
        "qualifier": null,
        "qualifier_svrty": null,
        "blunt_phrase": null,
        "terse_phrase": null,
        "clds": "CLR",
        "water_temp": null,
        "primary_wave_period": null,
        "primary_wave_height": null,
        "primary_swell_period": null,
        "primary_swell_height": null,
        "primary_swell_direction": null,
        "secondary_swell_period": null,
        "secondary_swell_height": null,
        "secondary_swell_direction": null
      },
      {
        "key": "OPKC",
        "class": "observation",
        "expire_time_gmt": 1776234600,
        "obs_id": "OPKC",
        "obs_name": "Karachi",
        "valid_time_gmt": 1776227400,
        "day_ind": "D",
        "temp": 84,
        "wx_icon": 21,
        "icon_extd": 2100,
        "wx_phrase": "Haze",
        "pressure_tend": null,
        "pressure_desc": null,
        "dewPt": 70,
        "heat_index": 88,
        "rh": 62,
        "pressure": 29.69,
        "vis": 1,
        "wc": 84,
        "wdir": 220,
        "wdir_cardinal": "SW",
        "gust": null,
        "wspd": 5,
        "max_temp": null,
        "min_temp": null,
        "precip_total": null,
        "precip_hrly": null,
        "snow_hrly": null,
        "uv_desc": "Moderate",
        "feels_like": 88,
        "uv_index": 5,
        "qualifier": null,
        "qualifier_svrty": null,
        "blunt_phrase": null,
        "terse_phrase": null,
        "clds": "CLR",
        "water_temp": null,
        "primary_wave_period": null,
        "primary_wave_height": null,
        "primary_swell_period": null,
        "primary_swell_height": null,
        "primary_swell_direction": null,
        "secondary_swell_period": null,
        "secondary_swell_height": null,
        "secondary_swell_direction": null
      },
      {
        "key": "OPKC",
        "class": "observation",
        "expire_time_gmt": 1776236400,
        "obs_id": "OPKC",
        "obs_name": "Karachi",
        "valid_time_gmt": 1776229200,
        "day_ind": "D",
        "temp": 86,
        "wx_icon": 21,
        "icon_extd": 2100,
        "wx_phrase": "Haze",
        "pressure_tend": null,
        "pressure_desc": null,
        "dewPt": 68,
        "heat_index": 89,
        "rh": 55,
        "pressure": 29.69,
        "vis": 2,
        "wc": 86,
        "wdir": 230,
        "wdir_cardinal": "SW",
        "gust": null,
        "wspd": 6,
        "max_temp": null,
        "min_temp": null,
        "precip_total": null,
        "precip_hrly": null,
        "snow_hrly": null,
        "uv_desc": "High",
        "feels_like": 89,
        "uv_index": 6,
        "qualifier": null,
        "qualifier_svrty": null,
        "blunt_phrase": null,
        "terse_phrase": null,
        "clds": "CLR",
        "water_temp": null,
        "primary_wave_period": null,
        "primary_wave_height": null,
        "primary_swell_period": null,
        "primary_swell_height": null,
        "primary_swell_direction": null,
        "secondary_swell_period": null,
        "secondary_swell_height": null,
        "secondary_swell_direction": null
      },
      {
        "key": "OPKC",
        "class": "observation",
        "expire_time_gmt": 1776238200,
        "obs_id": "OPKC",
        "obs_name": "Karachi",
        "valid_time_gmt": 1776231000,
        "day_ind": "D",
        "temp": 88,
        "wx_icon": 21,
        "icon_extd": 2100,
        "wx_phrase": "Haze",
        "pressure_tend": null,
        "pressure_desc": null,
        "dewPt": 68,
        "heat_index": 91,
        "rh": 52,
        "pressure": 29.69,
        "vis": 2,
        "wc": 88,
        "wdir": 240,
        "wdir_cardinal": "WSW",
        "gust": null,
        "wspd": 3,
        "max_temp": null,
        "min_temp": null,
        "precip_total": null,
        "precip_hrly": null,
        "snow_hrly": null,
        "uv_desc": "Very High",
        "feels_like": 91,
        "uv_index": 8,
        "qualifier": null,
        "qualifier_svrty": null,
        "blunt_phrase": null,
        "terse_phrase": null,
        "clds": "CLR",
        "water_temp": null,
        "primary_wave_period": null,
        "primary_wave_height": null,
        "primary_swell_period": null,
        "primary_swell_height": null,
        "primary_swell_direction": null,
        "secondary_swell_period": null,
        "secondary_swell_height": null,
        "secondary_swell_direction": null
      },
      {
        "key": "OPKC",
        "class": "observation",
        "expire_time_gmt": 1776240000,
        "obs_id": "OPKC",
        "obs_name": "Karachi",
        "valid_time_gmt": 1776232800,
        "day_ind": "D",
        "temp": 90,
        "wx_icon": 21,
        "icon_extd": 2100,
        "wx_phrase": "Haze",
        "pressure_tend": null,
        "pressure_desc": null,
        "dewPt": 66,
        "heat_index": 92,
        "rh": 46,
        "pressure": 29.69,
        "vis": 2,
        "wc": 90,
        "wdir": 200,
        "wdir_cardinal": "SSW",
        "gust": null,
        "wspd": 3,
        "max_temp": null,
        "min_temp": null,
        "precip_total": null,
        "precip_hrly": null,
        "snow_hrly": null,
        "uv_desc": "Very High",
        "feels_like": 92,
        "uv_index": 9,
        "qualifier": null,
        "qualifier_svrty": null,
        "blunt_phrase": null,
        "terse_phrase": null,
        "clds": "CLR",
        "water_temp": null,
        "primary_wave_period": null,
        "primary_wave_height": null,
        "primary_swell_period": null,
        "primary_swell_height": null,
        "primary_swell_direction": null,
        "secondary_swell_period": null,
        "secondary_swell_height": null,
        "secondary_swell_direction": null
      },
      {
        "key": "OPKC",
        "class": "observation",
        "expire_time_gmt": 1776241800,
        "obs_id": "OPKC",
        "obs_name": "Karachi",
        "valid_time_gmt": 1776234600,
        "day_ind": "D",
        "temp": 91,
        "wx_icon": 21,
        "icon_extd": 2100,
        "wx_phrase": "Haze",
        "pressure_tend": null,
        "pressure_desc": null,
        "dewPt": 68,
        "heat_index": 95,
        "rh": 46,
        "pressure": 29.69,
        "vis": 2,
        "wc": 91,
        "wdir": 230,
        "wdir_cardinal": "SW",
        "gust": null,
        "wspd": 9,
        "max_temp": null,
        "min_temp": null,
        "precip_total": null,
        "precip_hrly": null,
        "snow_hrly": null,
        "uv_desc": "Very High",
        "feels_like": 95,
        "uv_index": 10,
        "qualifier": null,
        "qualifier_svrty": null,
        "blunt_phrase": null,
        "terse_phrase": null,
        "clds": "CLR",
        "water_temp": null,
        "primary_wave_period": null,
        "primary_wave_height": null,
        "primary_swell_period": null,
        "primary_swell_height": null,
        "primary_swell_direction": null,
        "secondary_swell_period": null,
        "secondary_swell_height": null,
        "secondary_swell_direction": null
      },
      {
        "key": "OPKC",
        "class": "observation",
        "expire_time_gmt": 1776243600,
        "obs_id": "OPKC",
        "obs_name": "Karachi",
        "valid_time_gmt": 1776236400,
        "day_ind": "D",
        "temp": 91,
        "wx_icon": 21,
        "icon_extd": 2100,
        "wx_phrase": "Haze",
        "pressure_tend": null,
        "pressure_desc": null,
        "dewPt": 75,
        "heat_index": 102,
        "rh": 59,
        "pressure": 29.66,
        "vis": 2,
        "wc": 91,
        "wdir": 260,
        "wdir_cardinal": "W",
        "gust": null,
        "wspd": 9,
        "max_temp": null,
        "min_temp": null,
        "precip_total": null,
        "precip_hrly": null,
        "snow_hrly": null,
        "uv_desc": "Extreme",
        "feels_like": 102,
        "uv_index": 11,
        "qualifier": null,
        "qualifier_svrty": null,
        "blunt_phrase": null,
        "terse_phrase": null,
        "clds": "CLR",
        "water_temp": null,
        "primary_wave_period": null,
        "primary_wave_height": null,
        "primary_swell_period": null,
        "primary_swell_height": null,
        "primary_swell_direction": null,
        "secondary_swell_period": null,
        "secondary_swell_height": null,
        "secondary_swell_direction": null
      },
      {
        "key": "OPKC",
        "class": "observation",
        "expire_time_gmt": 1776245400,
        "obs_id": "OPKC",
        "obs_name": "Karachi",
        "valid_time_gmt": 1776238200,
        "day_ind": "D",
        "temp": 93,
        "wx_icon": 21,
        "icon_extd": 2100,
        "wx_phrase": "Haze",
        "pressure_tend": null,
        "pressure_desc": null,
        "dewPt": 68,
        "heat_index": 97,
        "rh": 44,
        "pressure": 29.66,
        "vis": 2,
        "wc": 93,
        "wdir": 210,
        "wdir_cardinal": "SSW",
        "gust": null,
        "wspd": 8,
        "max_temp": null,
        "min_temp": null,
        "precip_total": null,
        "precip_hrly": null,
        "snow_hrly": null,
        "uv_desc": "Extreme",
        "feels_like": 97,
        "uv_index": 12,
        "qualifier": null,
        "qualifier_svrty": null,
        "blunt_phrase": null,
        "terse_phrase": null,
        "clds": "CLR",
        "water_temp": null,
        "primary_wave_period": null,
        "primary_wave_height": null,
        "primary_swell_period": null,
        "primary_swell_height": null,
        "primary_swell_direction": null,
        "secondary_swell_period": null,
        "secondary_swell_height": null,
        "secondary_swell_direction": null
      },
      {
        "key": "OPKC",
        "class": "observation",
        "expire_time_gmt": 1776247200,
        "obs_id": "OPKC",
        "obs_name": "Karachi",
        "valid_time_gmt": 1776240000,
        "day_ind": "D",
        "temp": 93,
        "wx_icon": 21,
        "icon_extd": 2100,
        "wx_phrase": "Haze",
        "pressure_tend": null,
        "pressure_desc": null,
        "dewPt": 70,
        "heat_index": 99,
        "rh": 46,
        "pressure": 29.66,
        "vis": 2,
        "wc": 93,
        "wdir": 210,
        "wdir_cardinal": "SSW",
        "gust": null,
        "wspd": 16,
        "max_temp": null,
        "min_temp": null,
        "precip_total": null,
        "precip_hrly": null,
        "snow_hrly": null,
        "uv_desc": "Extreme",
        "feels_like": 99,
        "uv_index": 11,
        "qualifier": null,
        "qualifier_svrty": null,
        "blunt_phrase": null,
        "terse_phrase": null,
        "clds": "CLR",
        "water_temp": null,
        "primary_wave_period": null,
        "primary_wave_height": null,
        "primary_swell_period": null,
        "primary_swell_height": null,
        "primary_swell_direction": null,
        "secondary_swell_period": null,
        "secondary_swell_height": null,
        "secondary_swell_direction": null
      },
      {
        "key": "OPKC",
        "class": "observation",
        "expire_time_gmt": 1776249000,
        "obs_id": "OPKC",
        "obs_name": "Karachi",
        "valid_time_gmt": 1776241800,
        "day_ind": "D",
        "temp": 93,
        "wx_icon": 21,
        "icon_extd": 2100,
        "wx_phrase": "Haze",
        "pressure_tend": null,
        "pressure_desc": null,
        "dewPt": 70,
        "heat_index": 99,
        "rh": 46,
        "pressure": 29.66,
        "vis": 2,
        "wc": 93,
        "wdir": 220,
        "wdir_cardinal": "SW",
        "gust": null,
        "wspd": 14,
        "max_temp": null,
        "min_temp": null,
        "precip_total": null,
        "precip_hrly": null,
        "snow_hrly": null,
        "uv_desc": "Extreme",
        "feels_like": 99,
        "uv_index": 11,
        "qualifier": null,
        "qualifier_svrty": null,
        "blunt_phrase": null,
        "terse_phrase": null,
        "clds": "CLR",
        "water_temp": null,
        "primary_wave_period": null,
        "primary_wave_height": null,
        "primary_swell_period": null,
        "primary_swell_height": null,
        "primary_swell_direction": null,
        "secondary_swell_period": null,
        "secondary_swell_height": null,
        "secondary_swell_direction": null
      },
      {
        "key": "OPKC",
        "class": "observation",
        "expire_time_gmt": 1776250800,
        "obs_id": "OPKC",
        "obs_name": "Karachi",
        "valid_time_gmt": 1776243600,
        "day_ind": "D",
        "temp": 93,
        "wx_icon": 21,
        "icon_extd": 2100,
        "wx_phrase": "Haze",
        "pressure_tend": null,
        "pressure_desc": null,
        "dewPt": 70,
        "heat_index": 99,
        "rh": 46,
        "pressure": 29.63,
        "vis": 2,
        "wc": 93,
        "wdir": 210,
        "wdir_cardinal": "SSW",
        "gust": null,
        "wspd": 12,
        "max_temp": null,
        "min_temp": null,
        "precip_total": null,
        "precip_hrly": null,
        "snow_hrly": null,
        "uv_desc": "Very High",
        "feels_like": 99,
        "uv_index": 9,
        "qualifier": null,
        "qualifier_svrty": null,
        "blunt_phrase": null,
        "terse_phrase": null,
        "clds": "CLR",
        "water_temp": null,
        "primary_wave_period": null,
        "primary_wave_height": null,
        "primary_swell_period": null,
        "primary_swell_height": null,
        "primary_swell_direction": null,
        "secondary_swell_period": null,
        "secondary_swell_height": null,
        "secondary_swell_direction": null
      },
      {
        "key": "OPKC",
        "class": "observation",
        "expire_time_gmt": 1776252600,
        "obs_id": "OPKC",
        "obs_name": "Karachi",
        "valid_time_gmt": 1776245400,
        "day_ind": "D",
        "temp": 91,
        "wx_icon": 21,
        "icon_extd": 2100,
        "wx_phrase": "Haze",
        "pressure_tend": null,
        "pressure_desc": null,
        "dewPt": 68,
        "heat_index": 95,
        "rh": 46,
        "pressure": 29.63,
        "vis": 2,
        "wc": 91,
        "wdir": 210,
        "wdir_cardinal": "SSW",
        "gust": null,
        "wspd": 14,
        "max_temp": null,
        "min_temp": null,
        "precip_total": null,
        "precip_hrly": null,
        "snow_hrly": null,
        "uv_desc": "Very High",
        "feels_like": 95,
        "uv_index": 8,
        "qualifier": null,
        "qualifier_svrty": null,
        "blunt_phrase": null,
        "terse_phrase": null,
        "clds": "CLR",
        "water_temp": null,
        "primary_wave_period": null,
        "primary_wave_height": null,
        "primary_swell_period": null,
        "primary_swell_height": null,
        "primary_swell_direction": null,
        "secondary_swell_period": null,
        "secondary_swell_height": null,
        "secondary_swell_direction": null
      },
      {
        "key": "OPKC",
        "class": "observation",
        "expire_time_gmt": 1776254400,
        "obs_id": "OPKC",
        "obs_name": "Karachi",
        "valid_time_gmt": 1776247200,
        "day_ind": "D",
        "temp": 91,
        "wx_icon": 21,
        "icon_extd": 2100,
        "wx_phrase": "Haze",
        "pressure_tend": null,
        "pressure_desc": null,
        "dewPt": 68,
        "heat_index": 95,
        "rh": 46,
        "pressure": 29.6,
        "vis": 2,
        "wc": 91,
        "wdir": 230,
        "wdir_cardinal": "SW",
        "gust": null,
        "wspd": 12,
        "max_temp": null,
        "min_temp": null,
        "precip_total": null,
        "precip_hrly": null,
        "snow_hrly": null,
        "uv_desc": "High",
        "feels_like": 95,
        "uv_index": 7,
        "qualifier": null,
        "qualifier_svrty": null,
        "blunt_phrase": null,
        "terse_phrase": null,
        "clds": "CLR",
        "water_temp": null,
        "primary_wave_period": null,
        "primary_wave_height": null,
        "primary_swell_period": null,
        "primary_swell_height": null,
        "primary_swell_direction": null,
        "secondary_swell_period": null,
        "secondary_swell_height": null,
        "secondary_swell_direction": null
      },
      {
        "key": "OPKC",
        "class": "observation",
        "expire_time_gmt": 1776256200,
        "obs_id": "OPKC",
        "obs_name": "Karachi",
        "valid_time_gmt": 1776249000,
        "day_ind": "D",
        "temp": 93,
        "wx_icon": 21,
        "icon_extd": 2100,
        "wx_phrase": "Haze",
        "pressure_tend": null,
        "pressure_desc": null,
        "dewPt": 66,
        "heat_index": 96,
        "rh": 41,
        "pressure": 29.6,
        "vis": 2,
        "wc": 93,
        "wdir": 220,
        "wdir_cardinal": "SW",
        "gust": null,
        "wspd": 15,
        "max_temp": null,
        "min_temp": null,
        "precip_total": null,
        "precip_hrly": null,
        "snow_hrly": null,
        "uv_desc": "Moderate",
        "feels_like": 96,
        "uv_index": 5,
        "qualifier": null,
        "qualifier_svrty": null,
        "blunt_phrase": null,
        "terse_phrase": null,
        "clds": "CLR",
        "water_temp": null,
        "primary_wave_period": null,
        "primary_wave_height": null,
        "primary_swell_period": null,
        "primary_swell_height": null,
        "primary_swell_direction": null,
        "secondary_swell_period": null,
        "secondary_swell_height": null,
        "secondary_swell_direction": null
      },
      {
        "key": "OPKC",
        "class": "observation",
        "expire_time_gmt": 1776258000,
        "obs_id": "OPKC",
        "obs_name": "Karachi",
        "valid_time_gmt": 1776250800,
        "day_ind": "D",
        "temp": 93,
        "wx_icon": 21,
        "icon_extd": 2100,
        "wx_phrase": "Haze",
        "pressure_tend": null,
        "pressure_desc": null,
        "dewPt": 64,
        "heat_index": 95,
        "rh": 38,
        "pressure": 29.6,
        "vis": 2,
        "wc": 93,
        "wdir": 220,
        "wdir_cardinal": "SW",
        "gust": null,
        "wspd": 12,
        "max_temp": null,
        "min_temp": null,
        "precip_total": null,
        "precip_hrly": null,
        "snow_hrly": null,
        "uv_desc": "Moderate",
        "feels_like": 95,
        "uv_index": 4,
        "qualifier": null,
        "qualifier_svrty": null,
        "blunt_phrase": null,
        "terse_phrase": null,
        "clds": "CLR",
        "water_temp": null,
        "primary_wave_period": null,
        "primary_wave_height": null,
        "primary_swell_period": null,
        "primary_swell_height": null,
        "primary_swell_direction": null,
        "secondary_swell_period": null,
        "secondary_swell_height": null,
        "secondary_swell_direction": null
      },
      {
        "key": "OPKC",
        "class": "observation",
        "expire_time_gmt": 1776259800,
        "obs_id": "OPKC",
        "obs_name": "Karachi",
        "valid_time_gmt": 1776252600,
        "day_ind": "D",
        "temp": 93,
        "wx_icon": 21,
        "icon_extd": 2100,
        "wx_phrase": "Haze",
        "pressure_tend": null,
        "pressure_desc": null,
        "dewPt": 63,
        "heat_index": 94,
        "rh": 36,
        "pressure": 29.57,
        "vis": 3,
        "wc": 93,
        "wdir": 230,
        "wdir_cardinal": "SW",
        "gust": null,
        "wspd": 14,
        "max_temp": null,
        "min_temp": null,
        "precip_total": null,
        "precip_hrly": null,
        "snow_hrly": null,
        "uv_desc": "Low",
        "feels_like": 94,
        "uv_index": 2,
        "qualifier": null,
        "qualifier_svrty": null,
        "blunt_phrase": null,
        "terse_phrase": null,
        "clds": "CLR",
        "water_temp": null,
        "primary_wave_period": null,
        "primary_wave_height": null,
        "primary_swell_period": null,
        "primary_swell_height": null,
        "primary_swell_direction": null,
        "secondary_swell_period": null,
        "secondary_swell_height": null,
        "secondary_swell_direction": null
      },
      {
        "key": "OPKC",
        "class": "observation",
        "expire_time_gmt": 1776261600,
        "obs_id": "OPKC",
        "obs_name": "Karachi",
        "valid_time_gmt": 1776254400,
        "day_ind": "D",
        "temp": 91,
        "wx_icon": 21,
        "icon_extd": 2100,
        "wx_phrase": "Haze",
        "pressure_tend": null,
        "pressure_desc": null,
        "dewPt": 63,
        "heat_index": 92,
        "rh": 38,
        "pressure": 29.57,
        "vis": 3,
        "wc": 91,
        "wdir": 220,
        "wdir_cardinal": "SW",
        "gust": null,
        "wspd": 15,
        "max_temp": null,
        "min_temp": null,
        "precip_total": null,
        "precip_hrly": null,
        "snow_hrly": null,
        "uv_desc": "Low",
        "feels_like": 92,
        "uv_index": 1,
        "qualifier": null,
        "qualifier_svrty": null,
        "blunt_phrase": null,
        "terse_phrase": null,
        "clds": "CLR",
        "water_temp": null,
        "primary_wave_period": null,
        "primary_wave_height": null,
        "primary_swell_period": null,
        "primary_swell_height": null,
        "primary_swell_direction": null,
        "secondary_swell_period": null,
        "secondary_swell_height": null,
        "secondary_swell_direction": null
      },
      {
        "key": "OPKC",
        "class": "observation",
        "expire_time_gmt": 1776263400,
        "obs_id": "OPKC",
        "obs_name": "Karachi",
        "valid_time_gmt": 1776256200,
        "day_ind": "D",
        "temp": 88,
        "wx_icon": 21,
        "icon_extd": 2100,
        "wx_phrase": "Haze",
        "pressure_tend": null,
        "pressure_desc": null,
        "dewPt": 61,
        "heat_index": 88,
        "rh": 40,
        "pressure": 29.6,
        "vis": 3,
        "wc": 88,
        "wdir": 240,
        "wdir_cardinal": "WSW",
        "gust": null,
        "wspd": 14,
        "max_temp": null,
        "min_temp": null,
        "precip_total": null,
        "precip_hrly": null,
        "snow_hrly": null,
        "uv_desc": "Low",
        "feels_like": 88,
        "uv_index": 1,
        "qualifier": null,
        "qualifier_svrty": null,
        "blunt_phrase": null,
        "terse_phrase": null,
        "clds": "CLR",
        "water_temp": null,
        "primary_wave_period": null,
        "primary_wave_height": null,
        "primary_swell_period": null,
        "primary_swell_height": null,
        "primary_swell_direction": null,
        "secondary_swell_period": null,
        "secondary_swell_height": null,
        "secondary_swell_direction": null
      },
      {
        "key": "OPKC",
        "class": "observation",
        "expire_time_gmt": 1776265200,
        "obs_id": "OPKC",
        "obs_name": "Karachi",
        "valid_time_gmt": 1776258000,
        "day_ind": "D",
        "temp": 88,
        "wx_icon": 21,
        "icon_extd": 2100,
        "wx_phrase": "Haze",
        "pressure_tend": null,
        "pressure_desc": null,
        "dewPt": 61,
        "heat_index": 88,
        "rh": 40,
        "pressure": 29.6,
        "vis": 3,
        "wc": 88,
        "wdir": 240,
        "wdir_cardinal": "WSW",
        "gust": null,
        "wspd": 15,
        "max_temp": null,
        "min_temp": null,
        "precip_total": null,
        "precip_hrly": null,
        "snow_hrly": null,
        "uv_desc": "Low",
        "feels_like": 88,
        "uv_index": 0,
        "qualifier": null,
        "qualifier_svrty": null,
        "blunt_phrase": null,
        "terse_phrase": null,
        "clds": "CLR",
        "water_temp": null,
        "primary_wave_period": null,
        "primary_wave_height": null,
        "primary_swell_period": null,
        "primary_swell_height": null,
        "primary_swell_direction": null,
        "secondary_swell_period": null,
        "secondary_swell_height": null,
        "secondary_swell_direction": null
      },
      {
        "key": "OPKC",
        "class": "observation",
        "expire_time_gmt": 1776267000,
        "obs_id": "OPKC",
        "obs_name": "Karachi",
        "valid_time_gmt": 1776259800,
        "day_ind": "D",
        "temp": 86,
        "wx_icon": 21,
        "icon_extd": 2100,
        "wx_phrase": "Haze",
        "pressure_tend": null,
        "pressure_desc": null,
        "dewPt": 66,
        "heat_index": 88,
        "rh": 51,
        "pressure": 29.6,
        "vis": 3,
        "wc": 86,
        "wdir": 240,
        "wdir_cardinal": "WSW",
        "gust": null,
        "wspd": 16,
        "max_temp": null,
        "min_temp": null,
        "precip_total": null,
        "precip_hrly": null,
        "snow_hrly": null,
        "uv_desc": "Low",
        "feels_like": 88,
        "uv_index": 0,
        "qualifier": null,
        "qualifier_svrty": null,
        "blunt_phrase": null,
        "terse_phrase": null,
        "clds": "CLR",
        "water_temp": null,
        "primary_wave_period": null,
        "primary_wave_height": null,
        "primary_swell_period": null,
        "primary_swell_height": null,
        "primary_swell_direction": null,
        "secondary_swell_period": null,
        "secondary_swell_height": null,
        "secondary_swell_direction": null
      },
      {
        "key": "OPKC",
        "class": "observation",
        "expire_time_gmt": 1776268800,
        "obs_id": "OPKC",
        "obs_name": "Karachi",
        "valid_time_gmt": 1776261600,
        "day_ind": "N",
        "temp": 86,
        "wx_icon": 21,
        "icon_extd": 2100,
        "wx_phrase": "Haze",
        "pressure_tend": null,
        "pressure_desc": null,
        "dewPt": 66,
        "heat_index": 88,
        "rh": 51,
        "pressure": 29.6,
        "vis": 3,
        "wc": 86,
        "wdir": 240,
        "wdir_cardinal": "WSW",
        "gust": null,
        "wspd": 15,
        "max_temp": null,
        "min_temp": null,
        "precip_total": null,
        "precip_hrly": null,
        "snow_hrly": null,
        "uv_desc": "Low",
        "feels_like": 88,
        "uv_index": 0,
        "qualifier": null,
        "qualifier_svrty": null,
        "blunt_phrase": null,
        "terse_phrase": null,
        "clds": "CLR",
        "water_temp": null,
        "primary_wave_period": null,
        "primary_wave_height": null,
        "primary_swell_period": null,
        "primary_swell_height": null,
        "primary_swell_direction": null,
        "secondary_swell_period": null,
        "secondary_swell_height": null,
        "secondary_swell_direction": null
      },
      {
        "key": "OPKC",
        "class": "observation",
        "expire_time_gmt": 1776270600,
        "obs_id": "OPKC",
        "obs_name": "Karachi",
        "valid_time_gmt": 1776263400,
        "day_ind": "N",
        "temp": 84,
        "wx_icon": 21,
        "icon_extd": 2100,
        "wx_phrase": "Haze",
        "pressure_tend": null,
        "pressure_desc": null,
        "dewPt": 66,
        "heat_index": 86,
        "rh": 55,
        "pressure": 29.63,
        "vis": 3,
        "wc": 84,
        "wdir": 240,
        "wdir_cardinal": "WSW",
        "gust": null,
        "wspd": 13,
        "max_temp": null,
        "min_temp": null,
        "precip_total": null,
        "precip_hrly": null,
        "snow_hrly": null,
        "uv_desc": "Low",
        "feels_like": 86,
        "uv_index": 0,
        "qualifier": null,
        "qualifier_svrty": null,
        "blunt_phrase": null,
        "terse_phrase": null,
        "clds": "CLR",
        "water_temp": null,
        "primary_wave_period": null,
        "primary_wave_height": null,
        "primary_swell_period": null,
        "primary_swell_height": null,
        "primary_swell_direction": null,
        "secondary_swell_period": null,
        "secondary_swell_height": null,
        "secondary_swell_direction": null
      },
      {
        "key": "OPKC",
        "class": "observation",
        "expire_time_gmt": 1776272400,
        "obs_id": "OPKC",
        "obs_name": "Karachi",
        "valid_time_gmt": 1776265200,
        "day_ind": "N",
        "temp": 84,
        "wx_icon": 21,
        "icon_extd": 2100,
        "wx_phrase": "Haze",
        "pressure_tend": null,
        "pressure_desc": null,
        "dewPt": 66,
        "heat_index": 86,
        "rh": 55,
        "pressure": 29.63,
        "vis": 3,
        "wc": 84,
        "wdir": 240,
        "wdir_cardinal": "WSW",
        "gust": null,
        "wspd": 14,
        "max_temp": null,
        "min_temp": null,
        "precip_total": null,
        "precip_hrly": null,
        "snow_hrly": null,
        "uv_desc": "Low",
        "feels_like": 86,
        "uv_index": 0,
        "qualifier": null,
        "qualifier_svrty": null,
        "blunt_phrase": null,
        "terse_phrase": null,
        "clds": "CLR",
        "water_temp": null,
        "primary_wave_period": null,
        "primary_wave_height": null,
        "primary_swell_period": null,
        "primary_swell_height": null,
        "primary_swell_direction": null,
        "secondary_swell_period": null,
        "secondary_swell_height": null,
        "secondary_swell_direction": null
      },
      {
        "key": "OPKC",
        "class": "observation",
        "expire_time_gmt": 1776274200,
        "obs_id": "OPKC",
        "obs_name": "Karachi",
        "valid_time_gmt": 1776267000,
        "day_ind": "N",
        "temp": 82,
        "wx_icon": 21,
        "icon_extd": 2100,
        "wx_phrase": "Haze",
        "pressure_tend": null,
        "pressure_desc": null,
        "dewPt": 70,
        "heat_index": 86,
        "rh": 66,
        "pressure": 29.63,
        "vis": 3,
        "wc": 82,
        "wdir": 240,
        "wdir_cardinal": "WSW",
        "gust": null,
        "wspd": 13,
        "max_temp": null,
        "min_temp": null,
        "precip_total": null,
        "precip_hrly": null,
        "snow_hrly": null,
        "uv_desc": "Low",
        "feels_like": 86,
        "uv_index": 0,
        "qualifier": null,
        "qualifier_svrty": null,
        "blunt_phrase": null,
        "terse_phrase": null,
        "clds": "CLR",
        "water_temp": null,
        "primary_wave_period": null,
        "primary_wave_height": null,
        "primary_swell_period": null,
        "primary_swell_height": null,
        "primary_swell_direction": null,
        "secondary_swell_period": null,
        "secondary_swell_height": null,
        "secondary_swell_direction": null
      },
      {
        "key": "OPKC",
        "class": "observation",
        "expire_time_gmt": 1776276000,
        "obs_id": "OPKC",
        "obs_name": "Karachi",
        "valid_time_gmt": 1776268800,
        "day_ind": "N",
        "temp": 81,
        "wx_icon": 21,
        "icon_extd": 2100,
        "wx_phrase": "Haze",
        "pressure_tend": null,
        "pressure_desc": null,
        "dewPt": 70,
        "heat_index": 84,
        "rh": 70,
        "pressure": 29.66,
        "vis": 3,
        "wc": 81,
        "wdir": 240,
        "wdir_cardinal": "WSW",
        "gust": null,
        "wspd": 12,
        "max_temp": null,
        "min_temp": null,
        "precip_total": null,
        "precip_hrly": null,
        "snow_hrly": null,
        "uv_desc": "Low",
        "feels_like": 84,
        "uv_index": 0,
        "qualifier": null,
        "qualifier_svrty": null,
        "blunt_phrase": null,
        "terse_phrase": null,
        "clds": "CLR",
        "water_temp": null,
        "primary_wave_period": null,
        "primary_wave_height": null,
        "primary_swell_period": null,
        "primary_swell_height": null,
        "primary_swell_direction": null,
        "secondary_swell_period": null,
        "secondary_swell_height": null,
        "secondary_swell_direction": null
      },
      {
        "key": "OPKC",
        "class": "observation",
        "expire_time_gmt": 1776277800,
        "obs_id": "OPKC",
        "obs_name": "Karachi",
        "valid_time_gmt": 1776270600,
        "day_ind": "N",
        "temp": 81,
        "wx_icon": 21,
        "icon_extd": 2100,
        "wx_phrase": "Haze",
        "pressure_tend": null,
        "pressure_desc": null,
        "dewPt": 70,
        "heat_index": 84,
        "rh": 70,
        "pressure": 29.66,
        "vis": 3,
        "wc": 81,
        "wdir": 240,
        "wdir_cardinal": "WSW",
        "gust": null,
        "wspd": 13,
        "max_temp": null,
        "min_temp": null,
        "precip_total": null,
        "precip_hrly": null,
        "snow_hrly": null,
        "uv_desc": "Low",
        "feels_like": 84,
        "uv_index": 0,
        "qualifier": null,
        "qualifier_svrty": null,
        "blunt_phrase": null,
        "terse_phrase": null,
        "clds": "CLR",
        "water_temp": null,
        "primary_wave_period": null,
        "primary_wave_height": null,
        "primary_swell_period": null,
        "primary_swell_height": null,
        "primary_swell_direction": null,
        "secondary_swell_period": null,
        "secondary_swell_height": null,
        "secondary_swell_direction": null
      },
      {
        "key": "OPKC",
        "class": "observation",
        "expire_time_gmt": 1776279600,
        "obs_id": "OPKC",
        "obs_name": "Karachi",
        "valid_time_gmt": 1776272400,
        "day_ind": "N",
        "temp": 79,
        "wx_icon": 22,
        "icon_extd": 2200,
        "wx_phrase": "Smoke",
        "pressure_tend": null,
        "pressure_desc": null,
        "dewPt": 72,
        "heat_index": 82,
        "rh": 78,
        "pressure": 29.66,
        "vis": 3,
        "wc": 79,
        "wdir": 250,
        "wdir_cardinal": "WSW",
        "gust": null,
        "wspd": 6,
        "max_temp": null,
        "min_temp": null,
        "precip_total": null,
        "precip_hrly": null,
        "snow_hrly": null,
        "uv_desc": "Low",
        "feels_like": 82,
        "uv_index": 0,
        "qualifier": null,
        "qualifier_svrty": null,
        "blunt_phrase": null,
        "terse_phrase": null,
        "clds": "CLR",
        "water_temp": null,
        "primary_wave_period": null,
        "primary_wave_height": null,
        "primary_swell_period": null,
        "primary_swell_height": null,
        "primary_swell_direction": null,
        "secondary_swell_period": null,
        "secondary_swell_height": null,
        "secondary_swell_direction": null
      },
      {
        "key": "OPKC",
        "class": "observation",
        "expire_time_gmt": 1776281400,
        "obs_id": "OPKC",
        "obs_name": "Karachi",
        "valid_time_gmt": 1776274200,
        "day_ind": "N",
        "temp": 79,
        "wx_icon": 22,
        "icon_extd": 2200,
        "wx_phrase": "Smoke",
        "pressure_tend": null,
        "pressure_desc": null,
        "dewPt": 70,
        "heat_index": 81,
        "rh": 74,
        "pressure": 29.66,
        "vis": 3,
        "wc": 79,
        "wdir": 250,
        "wdir_cardinal": "WSW",
        "gust": null,
        "wspd": 7,
        "max_temp": null,
        "min_temp": null,
        "precip_total": null,
        "precip_hrly": null,
        "snow_hrly": null,
        "uv_desc": "Low",
        "feels_like": 81,
        "uv_index": 0,
        "qualifier": null,
        "qualifier_svrty": null,
        "blunt_phrase": null,
        "terse_phrase": null,
        "clds": "CLR",
        "water_temp": null,
        "primary_wave_period": null,
        "primary_wave_height": null,
        "primary_swell_period": null,
        "primary_swell_height": null,
        "primary_swell_direction": null,
        "secondary_swell_period": null,
        "secondary_swell_height": null,
        "secondary_swell_direction": null
      },
      {
        "key": "OPKC",
        "class": "observation",
        "expire_time_gmt": 1776283200,
        "obs_id": "OPKC",
        "obs_name": "Karachi",
        "valid_time_gmt": 1776276000,
        "day_ind": "N",
        "temp": 79,
        "wx_icon": 22,
        "icon_extd": 2200,
        "wx_phrase": "Smoke",
        "pressure_tend": null,
        "pressure_desc": null,
        "dewPt": 70,
        "heat_index": 81,
        "rh": 74,
        "pressure": 29.66,
        "vis": 3,
        "wc": 79,
        "wdir": 240,
        "wdir_cardinal": "WSW",
        "gust": null,
        "wspd": 6,
        "max_temp": null,
        "min_temp": null,
        "precip_total": null,
        "precip_hrly": null,
        "snow_hrly": null,
        "uv_desc": "Low",
        "feels_like": 81,
        "uv_index": 0,
        "qualifier": null,
        "qualifier_svrty": null,
        "blunt_phrase": null,
        "terse_phrase": null,
        "clds": "CLR",
        "water_temp": null,
        "primary_wave_period": null,
        "primary_wave_height": null,
        "primary_swell_period": null,
        "primary_swell_height": null,
        "primary_swell_direction": null,
        "secondary_swell_period": null,
        "secondary_swell_height": null,
        "secondary_swell_direction": null
      },
      {
        "key": "OPKC",
        "class": "observation",
        "expire_time_gmt": 1776285000,
        "obs_id": "OPKC",
        "obs_name": "Karachi",
        "valid_time_gmt": 1776277800,
        "day_ind": "N",
        "temp": 79,
        "wx_icon": 22,
        "icon_extd": 2200,
        "wx_phrase": "Smoke",
        "pressure_tend": null,
        "pressure_desc": null,
        "dewPt": 68,
        "heat_index": 81,
        "rh": 69,
        "pressure": 29.66,
        "vis": 3,
        "wc": 79,
        "wdir": 260,
        "wdir_cardinal": "W",
        "gust": null,
        "wspd": 5,
        "max_temp": null,
        "min_temp": null,
        "precip_total": null,
        "precip_hrly": null,
        "snow_hrly": null,
        "uv_desc": "Low",
        "feels_like": 81,
        "uv_index": 0,
        "qualifier": null,
        "qualifier_svrty": null,
        "blunt_phrase": null,
        "terse_phrase": null,
        "clds": "CLR",
        "water_temp": null,
        "primary_wave_period": null,
        "primary_wave_height": null,
        "primary_swell_period": null,
        "primary_swell_height": null,
        "primary_swell_direction": null,
        "secondary_swell_period": null,
        "secondary_swell_height": null,
        "secondary_swell_direction": null
      }
    ]
  }
}